<layer>
  <name>vw_cprm_geomar_al_facio</name>
  <id>LayerInfoImpl--5858a16e:18f82cf132b:-7f40</id>
  <type>VECTOR</type>
  <defaultStyle>
    <id>StyleInfoImpl-1ff15c00:18f8658b990:11d5</id>
  </defaultStyle>
  <styles class="linked-hash-set">
    <style>
      <id>StyleInfoImpl-1ff15c00:18f8658b990:11d5</id>
    </style>
  </styles>
  <resource class="featureType">
    <id>FeatureTypeInfoImpl--5858a16e:18f82cf132b:-7f41</id>
  </resource>
  <attribution>
    <logoWidth>0</logoWidth>
    <logoHeight>0</logoHeight>
  </attribution>
  <dateCreated>2024-05-16 19:43:01.700 UTC</dateCreated>
  <dateModified>2024-05-17 11:55:25.447 UTC</dateModified>
</layer>