<featureType>
  <id>FeatureTypeInfoImpl-357a6c89:190181d3427:-5e1d</id>
  <name>vw_ibge_rdv</name>
  <nativeName>vw_ibge_rdv</nativeName>
  <namespace>
    <id>NamespaceInfoImpl-1a496adc:189b7ad7362:-7fff</id>
  </namespace>
  <title>Rodovias</title>
  <keywords>
    <string>features</string>
    <string>vw_ibge_rdv</string>
  </keywords>
  <srs>EPSG:4674</srs>
  <nativeBoundingBox>
    <minx>-73.12333556113637</minx>
    <maxx>-34.796458302</maxx>
    <miny>-33.736623</miny>
    <maxy>4.7047222222</maxy>
    <crs>EPSG:4674</crs>
  </nativeBoundingBox>
  <latLonBoundingBox>
    <minx>-73.12333556113637</minx>
    <maxx>-34.79645830199999</maxx>
    <miny>-33.73662303207526</miny>
    <maxy>4.704722222227707</maxy>
    <crs>EPSG:4326</crs>
  </latLonBoundingBox>
  <projectionPolicy>FORCE_DECLARED</projectionPolicy>
  <enabled>true</enabled>
  <store class="dataStore">
    <id>DataStoreInfoImpl-1a496adc:189b7ad7362:-7ffe</id>
  </store>
  <serviceConfiguration>false</serviceConfiguration>
  <maxFeatures>0</maxFeatures>
  <numDecimals>0</numDecimals>
  <padWithZeros>false</padWithZeros>
  <forcedDecimal>false</forcedDecimal>
  <overridingServiceSRS>false</overridingServiceSRS>
  <skipNumberMatched>false</skipNumberMatched>
  <circularArcPresent>false</circularArcPresent>
</featureType>