<featureType>
  <id>FeatureTypeInfoImpl--5858a16e:18f82cf132b:-7e87</id>
  <name>vw_cprm_rr_lito</name>
  <nativeName>vw_cprm_rr_lito</nativeName>
  <namespace>
    <id>NamespaceInfoImpl-1a496adc:189b7ad7362:-7fff</id>
  </namespace>
  <title>Litologia SIG</title>
  <keywords>
    <string>features</string>
    <string>vw_cprm_rr_lito</string>
  </keywords>
  <srs>EPSG:4674</srs>
  <nativeBoundingBox>
    <minx>-64.82497055784495</minx>
    <maxx>-58.886818293229624</maxx>
    <miny>-1.580656246788294</miny>
    <maxy>5.271806862097037</maxy>
    <crs>EPSG:4674</crs>
  </nativeBoundingBox>
  <latLonBoundingBox>
    <minx>-64.82497055784495</minx>
    <maxx>-58.886818293229624</maxx>
    <miny>-1.5806562467431822</miny>
    <maxy>5.271806862179579</maxy>
    <crs>EPSG:4326</crs>
  </latLonBoundingBox>
  <projectionPolicy>FORCE_DECLARED</projectionPolicy>
  <enabled>true</enabled>
  <store class="dataStore">
    <id>DataStoreInfoImpl-1a496adc:189b7ad7362:-7ffe</id>
  </store>
  <serviceConfiguration>false</serviceConfiguration>
  <maxFeatures>0</maxFeatures>
  <numDecimals>0</numDecimals>
  <padWithZeros>false</padWithZeros>
  <forcedDecimal>false</forcedDecimal>
  <overridingServiceSRS>false</overridingServiceSRS>
  <skipNumberMatched>false</skipNumberMatched>
  <circularArcPresent>false</circularArcPresent>
</featureType>