<featureType>
  <id>FeatureTypeInfoImpl--5858a16e:18f82cf132b:-7ef9</id>
  <name>vw_cprm_mt_aflor</name>
  <nativeName>vw_cprm_mt_aflor</nativeName>
  <namespace>
    <id>NamespaceInfoImpl-1a496adc:189b7ad7362:-7fff</id>
  </namespace>
  <title>Afloramentos SIG</title>
  <keywords>
    <string>features</string>
    <string>vw_cprm_mt_aflor</string>
  </keywords>
  <srs>EPSG:4674</srs>
  <nativeBoundingBox>
    <minx>-61.56028</minx>
    <maxx>-51.04611</maxx>
    <miny>-17.63361000054536</miny>
    <maxy>-10.013330000323524</maxy>
    <crs>EPSG:4674</crs>
  </nativeBoundingBox>
  <latLonBoundingBox>
    <minx>-61.56028</minx>
    <maxx>-51.04610999999999</maxx>
    <miny>-17.633610008030868</miny>
    <maxy>-10.013330001674657</maxy>
    <crs>EPSG:4326</crs>
  </latLonBoundingBox>
  <projectionPolicy>FORCE_DECLARED</projectionPolicy>
  <enabled>true</enabled>
  <store class="dataStore">
    <id>DataStoreInfoImpl-1a496adc:189b7ad7362:-7ffe</id>
  </store>
  <serviceConfiguration>false</serviceConfiguration>
  <maxFeatures>0</maxFeatures>
  <numDecimals>0</numDecimals>
  <padWithZeros>false</padWithZeros>
  <forcedDecimal>false</forcedDecimal>
  <overridingServiceSRS>false</overridingServiceSRS>
  <skipNumberMatched>false</skipNumberMatched>
  <circularArcPresent>false</circularArcPresent>
</featureType>