<featureType>
  <id>FeatureTypeInfoImpl--5858a16e:18f82cf132b:-7e89</id>
  <name>vw_cprm_rr_estr</name>
  <nativeName>vw_cprm_rr_estr</nativeName>
  <namespace>
    <id>NamespaceInfoImpl-1a496adc:189b7ad7362:-7fff</id>
  </namespace>
  <title>Estruturas SIG</title>
  <keywords>
    <string>features</string>
    <string>vw_cprm_rr_estr</string>
  </keywords>
  <srs>EPSG:4674</srs>
  <nativeBoundingBox>
    <minx>-64.77281775899996</minx>
    <maxx>-58.895354484999984</maxx>
    <miny>-1.380745073999947</miny>
    <maxy>5.245911575000036</maxy>
    <crs>EPSG:4674</crs>
  </nativeBoundingBox>
  <latLonBoundingBox>
    <minx>-64.77281775899996</minx>
    <maxx>-58.895354484999984</maxx>
    <miny>-1.3807450739590892</miny>
    <maxy>5.245911575079714</maxy>
    <crs>EPSG:4326</crs>
  </latLonBoundingBox>
  <projectionPolicy>FORCE_DECLARED</projectionPolicy>
  <enabled>true</enabled>
  <store class="dataStore">
    <id>DataStoreInfoImpl-1a496adc:189b7ad7362:-7ffe</id>
  </store>
  <serviceConfiguration>false</serviceConfiguration>
  <maxFeatures>0</maxFeatures>
  <numDecimals>0</numDecimals>
  <padWithZeros>false</padWithZeros>
  <forcedDecimal>false</forcedDecimal>
  <overridingServiceSRS>false</overridingServiceSRS>
  <skipNumberMatched>false</skipNumberMatched>
  <circularArcPresent>false</circularArcPresent>
</featureType>