<featureType>
  <id>FeatureTypeInfoImpl--5858a16e:18f82cf132b:-7f05</id>
  <name>vw_cprm_ma_lin_estr</name>
  <nativeName>vw_cprm_ma_lin_estr</nativeName>
  <namespace>
    <id>NamespaceInfoImpl-1a496adc:189b7ad7362:-7fff</id>
  </namespace>
  <title>Lineamentos Estruturais SIG</title>
  <keywords>
    <string>features</string>
    <string>vw_cprm_ma_lin_estr</string>
  </keywords>
  <srs>EPSG:4674</srs>
  <nativeBoundingBox>
    <minx>-48.03833138974153</minx>
    <maxx>-41.59921613682113</maxx>
    <miny>-10.194145183494578</miny>
    <maxy>0.559298181482228</maxy>
    <crs>EPSG:4674</crs>
  </nativeBoundingBox>
  <latLonBoundingBox>
    <minx>-48.03833138974153</minx>
    <maxx>-41.59921613682112</maxx>
    <miny>-10.194145184928542</miny>
    <maxy>0.5592981814640937</maxy>
    <crs>EPSG:4326</crs>
  </latLonBoundingBox>
  <projectionPolicy>FORCE_DECLARED</projectionPolicy>
  <enabled>true</enabled>
  <store class="dataStore">
    <id>DataStoreInfoImpl-1a496adc:189b7ad7362:-7ffe</id>
  </store>
  <serviceConfiguration>false</serviceConfiguration>
  <maxFeatures>0</maxFeatures>
  <numDecimals>0</numDecimals>
  <padWithZeros>false</padWithZeros>
  <forcedDecimal>false</forcedDecimal>
  <overridingServiceSRS>false</overridingServiceSRS>
  <skipNumberMatched>false</skipNumberMatched>
  <circularArcPresent>false</circularArcPresent>
</featureType>